{"title": "FriendsBySmol", "id": "tg-1157032801921400837", "net.maunium.telegram.pack": {"short_name": "friendsbysmol", "hash": "-31026370"}, "stickers": [{"body": "☕", "url": "mxc://matrix.ang-cloud.ru/tTDYrvGrkwFxhDHaiTulOQeq", "info": {"w": 256, "h": 256, "size": 365482, "mimetype": "image/png", "thumbnail_url": "mxc://matrix.ang-cloud.ru/tTDYrvGrkwFxhDHaiTulOQeq", "thumbnail_info": {"w": 256, "h": 256, "size": 365482, "mimetype": "image/png"}}, "msgtype": "m.sticker", "id": "tg-1157032801921401407", "net.maunium.telegram.sticker": {"pack": {"id": "1157032801921400837", "short_name": "friendsbysmol"}, "id": "1157032801921401407", "emoticons": ["☕"]}}, {"body": "🎂", "url": "mxc://matrix.ang-cloud.ru/SPBizwFHVqmgpXUkPPORnJzX", "info": {"w": 256, "h": 256, "size": 508220, "mimetype": "image/png", "thumbnail_url": "mxc://matrix.ang-cloud.ru/SPBizwFHVqmgpXUkPPORnJzX", "thumbnail_info": {"w": 256, "h": 256, "size": 508220, "mimetype": "image/png"}}, "msgtype": "m.sticker", "id": "tg-1157032801921401409", "net.maunium.telegram.sticker": {"pack": {"id": "1157032801921400837", "short_name": "friendsbysmol"}, "id": "1157032801921401409", "emoticons": ["🎂"]}}, {"body": "💤", "url": "mxc://matrix.ang-cloud.ru/xssUAkedezrIlTyJJrSykkgl", "info": {"w": 256, "h": 256, "size": 329988, "mimetype": "image/png", "thumbnail_url": "mxc://matrix.ang-cloud.ru/xssUAkedezrIlTyJJrSykkgl", "thumbnail_info": {"w": 256, "h": 256, "size": 329988, "mimetype": "image/png"}}, "msgtype": "m.sticker", "id": "tg-1157032801921401411", "net.maunium.telegram.sticker": {"pack": {"id": "1157032801921400837", "short_name": "friendsbysmol"}, "id": "1157032801921401411", "emoticons": ["💤"]}}, {"body": "🛁", "url": "mxc://matrix.ang-cloud.ru/knZuoGtlfTqlYKDEbQpgyyia", "info": {"w": 256, "h": 256, "size": 367317, "mimetype": "image/png", "thumbnail_url": "mxc://matrix.ang-cloud.ru/knZuoGtlfTqlYKDEbQpgyyia", "thumbnail_info": {"w": 256, "h": 256, "size": 367317, "mimetype": "image/png"}}, "msgtype": "m.sticker", "id": "tg-1157032801921401413", "net.maunium.telegram.sticker": {"pack": {"id": "1157032801921400837", "short_name": "friendsbysmol"}, "id": "1157032801921401413", "emoticons": ["🛁"]}}, {"body": "☺️", "url": "mxc://matrix.ang-cloud.ru/ptXeDNwZfPCJCrLCgjbPktBt", "info": {"w": 256, "h": 256, "size": 442116, "mimetype": "image/png", "thumbnail_url": "mxc://matrix.ang-cloud.ru/ptXeDNwZfPCJCrLCgjbPktBt", "thumbnail_info": {"w": 256, "h": 256, "size": 442116, "mimetype": "image/png"}}, "msgtype": "m.sticker", "id": "tg-1157032801921401415", "net.maunium.telegram.sticker": {"pack": {"id": "1157032801921400837", "short_name": "friendsbysmol"}, "id": "1157032801921401415", "emoticons": ["☺"]}}, {"body": "🚬", "url": "mxc://matrix.ang-cloud.ru/JDnGNeJxFXjabVZUyGoNzKgU", "info": {"w": 256, "h": 256, "size": 257460, "mimetype": "image/png", "thumbnail_url": "mxc://matrix.ang-cloud.ru/JDnGNeJxFXjabVZUyGoNzKgU", "thumbnail_info": {"w": 256, "h": 256, "size": 257460, "mimetype": "image/png"}}, "msgtype": "m.sticker", "id": "tg-1157032801921401417", "net.maunium.telegram.sticker": {"pack": {"id": "1157032801921400837", "short_name": "friendsbysmol"}, "id": "1157032801921401417", "emoticons": ["🚬"]}}, {"body": "📖", "url": "mxc://matrix.ang-cloud.ru/zlBgRQJYVLtKCwvrblwWYSIY", "info": {"w": 256, "h": 256, "size": 450949, "mimetype": "image/png", "thumbnail_url": "mxc://matrix.ang-cloud.ru/zlBgRQJYVLtKCwvrblwWYSIY", "thumbnail_info": {"w": 256, "h": 256, "size": 450949, "mimetype": "image/png"}}, "msgtype": "m.sticker", "id": "tg-1157032801921401419", "net.maunium.telegram.sticker": {"pack": {"id": "1157032801921400837", "short_name": "friendsbysmol"}, "id": "1157032801921401419", "emoticons": ["📖"]}}, {"body": "❤", "url": "mxc://matrix.ang-cloud.ru/saTbMpzUejTAKvBGGvYoKgjt", "info": {"w": 256, "h": 256, "size": 423788, "mimetype": "image/png", "thumbnail_url": "mxc://matrix.ang-cloud.ru/saTbMpzUejTAKvBGGvYoKgjt", "thumbnail_info": {"w": 256, "h": 256, "size": 423788, "mimetype": "image/png"}}, "msgtype": "m.sticker", "id": "tg-1157032801921401421", "net.maunium.telegram.sticker": {"pack": {"id": "1157032801921400837", "short_name": "friendsbysmol"}, "id": "1157032801921401421", "emoticons": ["❤"]}}, {"body": "☕", "url": "mxc://matrix.ang-cloud.ru/ECavOfRjOFgbkShmkPNhsrFY", "info": {"w": 256, "h": 256, "size": 395352, "mimetype": "image/png", "thumbnail_url": "mxc://matrix.ang-cloud.ru/ECavOfRjOFgbkShmkPNhsrFY", "thumbnail_info": {"w": 256, "h": 256, "size": 395352, "mimetype": "image/png"}}, "msgtype": "m.sticker", "id": "tg-1157032801921401423", "net.maunium.telegram.sticker": {"pack": {"id": "1157032801921400837", "short_name": "friendsbysmol"}, "id": "1157032801921401423", "emoticons": ["☕"]}}, {"body": "🍷", "url": "mxc://matrix.ang-cloud.ru/PKsvCKzZQMqHcoVRFBQdgTNh", "info": {"w": 256, "h": 256, "size": 474733, "mimetype": "image/png", "thumbnail_url": "mxc://matrix.ang-cloud.ru/PKsvCKzZQMqHcoVRFBQdgTNh", "thumbnail_info": {"w": 256, "h": 256, "size": 474733, "mimetype": "image/png"}}, "msgtype": "m.sticker", "id": "tg-1157032801921401425", "net.maunium.telegram.sticker": {"pack": {"id": "1157032801921400837", "short_name": "friendsbysmol"}, "id": "1157032801921401425", "emoticons": ["🍷"]}}, {"body": "🍽", "url": "mxc://matrix.ang-cloud.ru/ctXAgOVozlvOnYvOrisWBBxi", "info": {"w": 256, "h": 256, "size": 281498, "mimetype": "image/png", "thumbnail_url": "mxc://matrix.ang-cloud.ru/ctXAgOVozlvOnYvOrisWBBxi", "thumbnail_info": {"w": 256, "h": 256, "size": 281498, "mimetype": "image/png"}}, "msgtype": "m.sticker", "id": "tg-1157032801921401427", "net.maunium.telegram.sticker": {"pack": {"id": "1157032801921400837", "short_name": "friendsbysmol"}, "id": "1157032801921401427", "emoticons": ["🍽"]}}, {"body": "🍕", "url": "mxc://matrix.ang-cloud.ru/aBjTVWOXDsWtKwvKMUmTvvFl", "info": {"w": 256, "h": 256, "size": 440006, "mimetype": "image/png", "thumbnail_url": "mxc://matrix.ang-cloud.ru/aBjTVWOXDsWtKwvKMUmTvvFl", "thumbnail_info": {"w": 256, "h": 256, "size": 440006, "mimetype": "image/png"}}, "msgtype": "m.sticker", "id": "tg-1157032801921401430", "net.maunium.telegram.sticker": {"pack": {"id": "1157032801921400837", "short_name": "friendsbysmol"}, "id": "1157032801921401430", "emoticons": ["🍕"]}}, {"body": "🎂", "url": "mxc://matrix.ang-cloud.ru/vUebhBOkmEssWpaPLLASIRsQ", "info": {"w": 256, "h": 256, "size": 386329, "mimetype": "image/png", "thumbnail_url": "mxc://matrix.ang-cloud.ru/vUebhBOkmEssWpaPLLASIRsQ", "thumbnail_info": {"w": 256, "h": 256, "size": 386329, "mimetype": "image/png"}}, "msgtype": "m.sticker", "id": "tg-1157032801921401432", "net.maunium.telegram.sticker": {"pack": {"id": "1157032801921400837", "short_name": "friendsbysmol"}, "id": "1157032801921401432", "emoticons": ["🎂"]}}, {"body": "🍺", "url": "mxc://matrix.ang-cloud.ru/cjIyTBAvqETRDujmowSmpDMT", "info": {"w": 256, "h": 256, "size": 348934, "mimetype": "image/png", "thumbnail_url": "mxc://matrix.ang-cloud.ru/cjIyTBAvqETRDujmowSmpDMT", "thumbnail_info": {"w": 256, "h": 256, "size": 348934, "mimetype": "image/png"}}, "msgtype": "m.sticker", "id": "tg-1157032801921401434", "net.maunium.telegram.sticker": {"pack": {"id": "1157032801921400837", "short_name": "friendsbysmol"}, "id": "1157032801921401434", "emoticons": ["🍺"]}}, {"body": "😖", "url": "mxc://matrix.ang-cloud.ru/qGncRyDfXFENpQRkqgFSejQb", "info": {"w": 256, "h": 256, "size": 459727, "mimetype": "image/png", "thumbnail_url": "mxc://matrix.ang-cloud.ru/qGncRyDfXFENpQRkqgFSejQb", "thumbnail_info": {"w": 256, "h": 256, "size": 459727, "mimetype": "image/png"}}, "msgtype": "m.sticker", "id": "tg-1157032801921401436", "net.maunium.telegram.sticker": {"pack": {"id": "1157032801921400837", "short_name": "friendsbysmol"}, "id": "1157032801921401436", "emoticons": ["😖"]}}, {"body": "😱", "url": "mxc://matrix.ang-cloud.ru/fYiOiNsLCtaUFLjZNUzFVGTj", "info": {"w": 256, "h": 256, "size": 373415, "mimetype": "image/png", "thumbnail_url": "mxc://matrix.ang-cloud.ru/fYiOiNsLCtaUFLjZNUzFVGTj", "thumbnail_info": {"w": 256, "h": 256, "size": 373415, "mimetype": "image/png"}}, "msgtype": "m.sticker", "id": "tg-1157032801921401438", "net.maunium.telegram.sticker": {"pack": {"id": "1157032801921400837", "short_name": "friendsbysmol"}, "id": "1157032801921401438", "emoticons": ["😱"]}}, {"body": "✊", "url": "mxc://matrix.ang-cloud.ru/nwvQeiXinCMbAiyUcfoLYvfe", "info": {"w": 256, "h": 256, "size": 480836, "mimetype": "image/png", "thumbnail_url": "mxc://matrix.ang-cloud.ru/nwvQeiXinCMbAiyUcfoLYvfe", "thumbnail_info": {"w": 256, "h": 256, "size": 480836, "mimetype": "image/png"}}, "msgtype": "m.sticker", "id": "tg-1157032801921401440", "net.maunium.telegram.sticker": {"pack": {"id": "1157032801921400837", "short_name": "friendsbysmol"}, "id": "1157032801921401440", "emoticons": ["✊"]}}, {"body": "👰", "url": "mxc://matrix.ang-cloud.ru/yAAQemefmwsFgqYGvzgwuOkv", "info": {"w": 256, "h": 256, "size": 315248, "mimetype": "image/png", "thumbnail_url": "mxc://matrix.ang-cloud.ru/yAAQemefmwsFgqYGvzgwuOkv", "thumbnail_info": {"w": 256, "h": 256, "size": 315248, "mimetype": "image/png"}}, "msgtype": "m.sticker", "id": "tg-1157032801921401442", "net.maunium.telegram.sticker": {"pack": {"id": "1157032801921400837", "short_name": "friendsbysmol"}, "id": "1157032801921401442", "emoticons": ["👰"]}}, {"body": "🗑", "url": "mxc://matrix.ang-cloud.ru/vRLMknzIWmkJnzxeeaEabarp", "info": {"w": 256, "h": 256, "size": 497057, "mimetype": "image/png", "thumbnail_url": "mxc://matrix.ang-cloud.ru/vRLMknzIWmkJnzxeeaEabarp", "thumbnail_info": {"w": 256, "h": 256, "size": 497057, "mimetype": "image/png"}}, "msgtype": "m.sticker", "id": "tg-1157032801921401444", "net.maunium.telegram.sticker": {"pack": {"id": "1157032801921400837", "short_name": "friendsbysmol"}, "id": "1157032801921401444", "emoticons": ["🗑"]}}, {"body": "☹", "url": "mxc://matrix.ang-cloud.ru/HPaLbzOAbZpmygMvRiwXJdjf", "info": {"w": 256, "h": 256, "size": 398782, "mimetype": "image/png", "thumbnail_url": "mxc://matrix.ang-cloud.ru/HPaLbzOAbZpmygMvRiwXJdjf", "thumbnail_info": {"w": 256, "h": 256, "size": 398782, "mimetype": "image/png"}}, "msgtype": "m.sticker", "id": "tg-1157032801921401446", "net.maunium.telegram.sticker": {"pack": {"id": "1157032801921400837", "short_name": "friendsbysmol"}, "id": "1157032801921401446", "emoticons": ["☹"]}}, {"body": "😴", "url": "mxc://matrix.ang-cloud.ru/wzIAAIQDrQEbEPBjueXIvNRs", "info": {"w": 256, "h": 256, "size": 352167, "mimetype": "image/png", "thumbnail_url": "mxc://matrix.ang-cloud.ru/wzIAAIQDrQEbEPBjueXIvNRs", "thumbnail_info": {"w": 256, "h": 256, "size": 352167, "mimetype": "image/png"}}, "msgtype": "m.sticker", "id": "tg-1157032801921401448", "net.maunium.telegram.sticker": {"pack": {"id": "1157032801921400837", "short_name": "friendsbysmol"}, "id": "1157032801921401448", "emoticons": ["😴"]}}, {"body": "🍹", "url": "mxc://matrix.ang-cloud.ru/WUzUcTJbqQvfpIkfpitXryhh", "info": {"w": 256, "h": 256, "size": 488708, "mimetype": "image/png", "thumbnail_url": "mxc://matrix.ang-cloud.ru/WUzUcTJbqQvfpIkfpitXryhh", "thumbnail_info": {"w": 256, "h": 256, "size": 488708, "mimetype": "image/png"}}, "msgtype": "m.sticker", "id": "tg-1157032801921401450", "net.maunium.telegram.sticker": {"pack": {"id": "1157032801921400837", "short_name": "friendsbysmol"}, "id": "1157032801921401450", "emoticons": ["🍹"]}}, {"body": "☕", "url": "mxc://matrix.ang-cloud.ru/FhilJDnXvmhhWxNQWrRDZhoa", "info": {"w": 256, "h": 256, "size": 492230, "mimetype": "image/png", "thumbnail_url": "mxc://matrix.ang-cloud.ru/FhilJDnXvmhhWxNQWrRDZhoa", "thumbnail_info": {"w": 256, "h": 256, "size": 492230, "mimetype": "image/png"}}, "msgtype": "m.sticker", "id": "tg-1157032801921401452", "net.maunium.telegram.sticker": {"pack": {"id": "1157032801921400837", "short_name": "friendsbysmol"}, "id": "1157032801921401452", "emoticons": ["☕"]}}, {"body": "🤗", "url": "mxc://matrix.ang-cloud.ru/DPkhBpLRnjDtQTjqbkbBJJhe", "info": {"w": 256, "h": 256, "size": 432087, "mimetype": "image/png", "thumbnail_url": "mxc://matrix.ang-cloud.ru/DPkhBpLRnjDtQTjqbkbBJJhe", "thumbnail_info": {"w": 256, "h": 256, "size": 432087, "mimetype": "image/png"}}, "msgtype": "m.sticker", "id": "tg-1157032801921401454", "net.maunium.telegram.sticker": {"pack": {"id": "1157032801921400837", "short_name": "friendsbysmol"}, "id": "1157032801921401454", "emoticons": ["🤗"]}}, {"body": "🍸", "url": "mxc://matrix.ang-cloud.ru/tnxymetExxoEjQRjqsWBfyWv", "info": {"w": 256, "h": 256, "size": 309869, "mimetype": "image/png", "thumbnail_url": "mxc://matrix.ang-cloud.ru/tnxymetExxoEjQRjqsWBfyWv", "thumbnail_info": {"w": 256, "h": 256, "size": 309869, "mimetype": "image/png"}}, "msgtype": "m.sticker", "id": "tg-1157032801921401456", "net.maunium.telegram.sticker": {"pack": {"id": "1157032801921400837", "short_name": "friendsbysmol"}, "id": "1157032801921401456", "emoticons": ["🍸"]}}, {"body": "👦", "url": "mxc://matrix.ang-cloud.ru/PrfxGEYgpkTUFSHIZbSMdDcn", "info": {"w": 256, "h": 256, "size": 413650, "mimetype": "image/png", "thumbnail_url": "mxc://matrix.ang-cloud.ru/PrfxGEYgpkTUFSHIZbSMdDcn", "thumbnail_info": {"w": 256, "h": 256, "size": 413650, "mimetype": "image/png"}}, "msgtype": "m.sticker", "id": "tg-1157032801921401458", "net.maunium.telegram.sticker": {"pack": {"id": "1157032801921400837", "short_name": "friendsbysmol"}, "id": "1157032801921401458", "emoticons": ["👦"]}}, {"body": "🎧", "url": "mxc://matrix.ang-cloud.ru/thsCPUsoaRPBQJYIWEATDhaD", "info": {"w": 256, "h": 256, "size": 296718, "mimetype": "image/png", "thumbnail_url": "mxc://matrix.ang-cloud.ru/thsCPUsoaRPBQJYIWEATDhaD", "thumbnail_info": {"w": 256, "h": 256, "size": 296718, "mimetype": "image/png"}}, "msgtype": "m.sticker", "id": "tg-1157032801921401460", "net.maunium.telegram.sticker": {"pack": {"id": "1157032801921400837", "short_name": "friendsbysmol"}, "id": "1157032801921401460", "emoticons": ["🎧"]}}, {"body": "😳", "url": "mxc://matrix.ang-cloud.ru/zarMQnHeiAMyrMeJDqhvBCse", "info": {"w": 256, "h": 256, "size": 311494, "mimetype": "image/png", "thumbnail_url": "mxc://matrix.ang-cloud.ru/zarMQnHeiAMyrMeJDqhvBCse", "thumbnail_info": {"w": 256, "h": 256, "size": 311494, "mimetype": "image/png"}}, "msgtype": "m.sticker", "id": "tg-1157032801921401462", "net.maunium.telegram.sticker": {"pack": {"id": "1157032801921400837", "short_name": "friendsbysmol"}, "id": "1157032801921401462", "emoticons": ["😳"]}}, {"body": "💏", "url": "mxc://matrix.ang-cloud.ru/nMxWSOjINGATPsnkSLBksrza", "info": {"w": 256, "h": 256, "size": 390550, "mimetype": "image/png", "thumbnail_url": "mxc://matrix.ang-cloud.ru/nMxWSOjINGATPsnkSLBksrza", "thumbnail_info": {"w": 256, "h": 256, "size": 390550, "mimetype": "image/png"}}, "msgtype": "m.sticker", "id": "tg-1157032801921401465", "net.maunium.telegram.sticker": {"pack": {"id": "1157032801921400837", "short_name": "friendsbysmol"}, "id": "1157032801921401465", "emoticons": ["💏"]}}, {"body": "🛁", "url": "mxc://matrix.ang-cloud.ru/iAFmYdMSSeVhvmqtTYhTYrqK", "info": {"w": 256, "h": 256, "size": 339754, "mimetype": "image/png", "thumbnail_url": "mxc://matrix.ang-cloud.ru/iAFmYdMSSeVhvmqtTYhTYrqK", "thumbnail_info": {"w": 256, "h": 256, "size": 339754, "mimetype": "image/png"}}, "msgtype": "m.sticker", "id": "tg-1157032801921401467", "net.maunium.telegram.sticker": {"pack": {"id": "1157032801921400837", "short_name": "friendsbysmol"}, "id": "1157032801921401467", "emoticons": ["🛁"]}}, {"body": "😏", "url": "mxc://matrix.ang-cloud.ru/GpYuWUpnLwJzfByqFoHvDxxS", "info": {"w": 256, "h": 256, "size": 315348, "mimetype": "image/png", "thumbnail_url": "mxc://matrix.ang-cloud.ru/GpYuWUpnLwJzfByqFoHvDxxS", "thumbnail_info": {"w": 256, "h": 256, "size": 315348, "mimetype": "image/png"}}, "msgtype": "m.sticker", "id": "tg-1157032801921401469", "net.maunium.telegram.sticker": {"pack": {"id": "1157032801921400837", "short_name": "friendsbysmol"}, "id": "1157032801921401469", "emoticons": ["😏"]}}, {"body": "😮", "url": "mxc://matrix.ang-cloud.ru/LuDzWoogBerCNpxRXnHqyUhv", "info": {"w": 256, "h": 256, "size": 408575, "mimetype": "image/png", "thumbnail_url": "mxc://matrix.ang-cloud.ru/LuDzWoogBerCNpxRXnHqyUhv", "thumbnail_info": {"w": 256, "h": 256, "size": 408575, "mimetype": "image/png"}}, "msgtype": "m.sticker", "id": "tg-1157032801921401471", "net.maunium.telegram.sticker": {"pack": {"id": "1157032801921400837", "short_name": "friendsbysmol"}, "id": "1157032801921401471", "emoticons": ["😮"]}}, {"body": "🗽", "url": "mxc://matrix.ang-cloud.ru/ocCDPCGbDqZBgxeONmidfpwf", "info": {"w": 256, "h": 256, "size": 340265, "mimetype": "image/png", "thumbnail_url": "mxc://matrix.ang-cloud.ru/ocCDPCGbDqZBgxeONmidfpwf", "thumbnail_info": {"w": 256, "h": 256, "size": 340265, "mimetype": "image/png"}}, "msgtype": "m.sticker", "id": "tg-1157032801921401473", "net.maunium.telegram.sticker": {"pack": {"id": "1157032801921400837", "short_name": "friendsbysmol"}, "id": "1157032801921401473", "emoticons": ["🗽"]}}, {"body": "🤔", "url": "mxc://matrix.ang-cloud.ru/yYLayHNZVhGrfKBMBNVJUAbT", "info": {"w": 256, "h": 256, "size": 334002, "mimetype": "image/png", "thumbnail_url": "mxc://matrix.ang-cloud.ru/yYLayHNZVhGrfKBMBNVJUAbT", "thumbnail_info": {"w": 256, "h": 256, "size": 334002, "mimetype": "image/png"}}, "msgtype": "m.sticker", "id": "tg-1157032801921401475", "net.maunium.telegram.sticker": {"pack": {"id": "1157032801921400837", "short_name": "friendsbysmol"}, "id": "1157032801921401475", "emoticons": ["🤔"]}}, {"body": "🍻", "url": "mxc://matrix.ang-cloud.ru/SSDQWwyvwLyZODJFOKgxLRgc", "info": {"w": 256, "h": 256, "size": 387434, "mimetype": "image/png", "thumbnail_url": "mxc://matrix.ang-cloud.ru/SSDQWwyvwLyZODJFOKgxLRgc", "thumbnail_info": {"w": 256, "h": 256, "size": 387434, "mimetype": "image/png"}}, "msgtype": "m.sticker", "id": "tg-1157032801921401478", "net.maunium.telegram.sticker": {"pack": {"id": "1157032801921400837", "short_name": "friendsbysmol"}, "id": "1157032801921401478", "emoticons": ["🍻"]}}, {"body": "😜", "url": "mxc://matrix.ang-cloud.ru/KguCMrqAPngCGuegNtmsRMkM", "info": {"w": 256, "h": 256, "size": 352196, "mimetype": "image/png", "thumbnail_url": "mxc://matrix.ang-cloud.ru/KguCMrqAPngCGuegNtmsRMkM", "thumbnail_info": {"w": 256, "h": 256, "size": 352196, "mimetype": "image/png"}}, "msgtype": "m.sticker", "id": "tg-1157032801921401480", "net.maunium.telegram.sticker": {"pack": {"id": "1157032801921400837", "short_name": "friendsbysmol"}, "id": "1157032801921401480", "emoticons": ["😜"]}}, {"body": "😐", "url": "mxc://matrix.ang-cloud.ru/ypFZCnqjOyVsjGjoCmsWsumE", "info": {"w": 256, "h": 256, "size": 460488, "mimetype": "image/png", "thumbnail_url": "mxc://matrix.ang-cloud.ru/ypFZCnqjOyVsjGjoCmsWsumE", "thumbnail_info": {"w": 256, "h": 256, "size": 460488, "mimetype": "image/png"}}, "msgtype": "m.sticker", "id": "tg-1157032801921401482", "net.maunium.telegram.sticker": {"pack": {"id": "1157032801921400837", "short_name": "friendsbysmol"}, "id": "1157032801921401482", "emoticons": ["😐"]}}, {"body": "🤒", "url": "mxc://matrix.ang-cloud.ru/wjGprtXyFvrAamcNNOxpGZNF", "info": {"w": 256, "h": 256, "size": 404357, "mimetype": "image/png", "thumbnail_url": "mxc://matrix.ang-cloud.ru/wjGprtXyFvrAamcNNOxpGZNF", "thumbnail_info": {"w": 256, "h": 256, "size": 404357, "mimetype": "image/png"}}, "msgtype": "m.sticker", "id": "tg-1157032801921401484", "net.maunium.telegram.sticker": {"pack": {"id": "1157032801921400837", "short_name": "friendsbysmol"}, "id": "1157032801921401484", "emoticons": ["🤒"]}}, {"body": "🍕", "url": "mxc://matrix.ang-cloud.ru/XvMRCECeyduVlKXGBURxaRpC", "info": {"w": 256, "h": 256, "size": 506228, "mimetype": "image/png", "thumbnail_url": "mxc://matrix.ang-cloud.ru/XvMRCECeyduVlKXGBURxaRpC", "thumbnail_info": {"w": 256, "h": 256, "size": 506228, "mimetype": "image/png"}}, "msgtype": "m.sticker", "id": "tg-1157032801921401486", "net.maunium.telegram.sticker": {"pack": {"id": "1157032801921400837", "short_name": "friendsbysmol"}, "id": "1157032801921401486", "emoticons": ["🍕"]}}, {"body": "👍", "url": "mxc://matrix.ang-cloud.ru/XleQevJcfApkqUfJGOpKGEAz", "info": {"w": 256, "h": 256, "size": 365153, "mimetype": "image/png", "thumbnail_url": "mxc://matrix.ang-cloud.ru/XleQevJcfApkqUfJGOpKGEAz", "thumbnail_info": {"w": 256, "h": 256, "size": 365153, "mimetype": "image/png"}}, "msgtype": "m.sticker", "id": "tg-1157032801921401488", "net.maunium.telegram.sticker": {"pack": {"id": "1157032801921400837", "short_name": "friendsbysmol"}, "id": "1157032801921401488", "emoticons": ["👍"]}}, {"body": "👸", "url": "mxc://matrix.ang-cloud.ru/nOSIMVSHOXRAmUolVEbveWHF", "info": {"w": 256, "h": 256, "size": 377915, "mimetype": "image/png", "thumbnail_url": "mxc://matrix.ang-cloud.ru/nOSIMVSHOXRAmUolVEbveWHF", "thumbnail_info": {"w": 256, "h": 256, "size": 377915, "mimetype": "image/png"}}, "msgtype": "m.sticker", "id": "tg-1157032801921401490", "net.maunium.telegram.sticker": {"pack": {"id": "1157032801921400837", "short_name": "friendsbysmol"}, "id": "1157032801921401490", "emoticons": ["👸"]}}, {"body": "💸", "url": "mxc://matrix.ang-cloud.ru/rtPxaoCDdyTASjwcbaoJUtIV", "info": {"w": 256, "h": 256, "size": 393025, "mimetype": "image/png", "thumbnail_url": "mxc://matrix.ang-cloud.ru/rtPxaoCDdyTASjwcbaoJUtIV", "thumbnail_info": {"w": 256, "h": 256, "size": 393025, "mimetype": "image/png"}}, "msgtype": "m.sticker", "id": "tg-1157032801921401492", "net.maunium.telegram.sticker": {"pack": {"id": "1157032801921400837", "short_name": "friendsbysmol"}, "id": "1157032801921401492", "emoticons": ["💸"]}}, {"body": "🏃", "url": "mxc://matrix.ang-cloud.ru/vdUkvHsiNJCgPIuOodrAmNFh", "info": {"w": 256, "h": 256, "size": 305727, "mimetype": "image/png", "thumbnail_url": "mxc://matrix.ang-cloud.ru/vdUkvHsiNJCgPIuOodrAmNFh", "thumbnail_info": {"w": 256, "h": 256, "size": 305727, "mimetype": "image/png"}}, "msgtype": "m.sticker", "id": "tg-1157032801921401494", "net.maunium.telegram.sticker": {"pack": {"id": "1157032801921400837", "short_name": "friendsbysmol"}, "id": "1157032801921401494", "emoticons": ["🏃"]}}, {"body": "🎷", "url": "mxc://matrix.ang-cloud.ru/pGyofXKSsNDjPxZCYlRyGRuU", "info": {"w": 256, "h": 256, "size": 381582, "mimetype": "image/png", "thumbnail_url": "mxc://matrix.ang-cloud.ru/pGyofXKSsNDjPxZCYlRyGRuU", "thumbnail_info": {"w": 256, "h": 256, "size": 381582, "mimetype": "image/png"}}, "msgtype": "m.sticker", "id": "tg-1157032801921401496", "net.maunium.telegram.sticker": {"pack": {"id": "1157032801921400837", "short_name": "friendsbysmol"}, "id": "1157032801921401496", "emoticons": ["🎷"]}}, {"body": "😳", "url": "mxc://matrix.ang-cloud.ru/CcErPSkxNArfHEkOGWqwxtwi", "info": {"w": 256, "h": 256, "size": 381793, "mimetype": "image/png", "thumbnail_url": "mxc://matrix.ang-cloud.ru/CcErPSkxNArfHEkOGWqwxtwi", "thumbnail_info": {"w": 256, "h": 256, "size": 381793, "mimetype": "image/png"}}, "msgtype": "m.sticker", "id": "tg-1157032801921401498", "net.maunium.telegram.sticker": {"pack": {"id": "1157032801921400837", "short_name": "friendsbysmol"}, "id": "1157032801921401498", "emoticons": ["😳"]}}, {"body": "😊", "url": "mxc://matrix.ang-cloud.ru/VCMIAhJrCwThCqojwncmGvyO", "info": {"w": 256, "h": 256, "size": 401150, "mimetype": "image/png", "thumbnail_url": "mxc://matrix.ang-cloud.ru/VCMIAhJrCwThCqojwncmGvyO", "thumbnail_info": {"w": 256, "h": 256, "size": 401150, "mimetype": "image/png"}}, "msgtype": "m.sticker", "id": "tg-1157032801921401500", "net.maunium.telegram.sticker": {"pack": {"id": "1157032801921400837", "short_name": "friendsbysmol"}, "id": "1157032801921401500", "emoticons": ["😊"]}}, {"body": "😴", "url": "mxc://matrix.ang-cloud.ru/PcwjURtjxmuNdGtwnHpmGabA", "info": {"w": 256, "h": 256, "size": 359851, "mimetype": "image/png", "thumbnail_url": "mxc://matrix.ang-cloud.ru/PcwjURtjxmuNdGtwnHpmGabA", "thumbnail_info": {"w": 256, "h": 256, "size": 359851, "mimetype": "image/png"}}, "msgtype": "m.sticker", "id": "tg-1157032801921401502", "net.maunium.telegram.sticker": {"pack": {"id": "1157032801921400837", "short_name": "friendsbysmol"}, "id": "1157032801921401502", "emoticons": ["😴"]}}, {"body": "😳", "url": "mxc://matrix.ang-cloud.ru/pHOlMuwdkbeyOPTPiniwgsAs", "info": {"w": 256, "h": 256, "size": 350376, "mimetype": "image/png", "thumbnail_url": "mxc://matrix.ang-cloud.ru/pHOlMuwdkbeyOPTPiniwgsAs", "thumbnail_info": {"w": 256, "h": 256, "size": 350376, "mimetype": "image/png"}}, "msgtype": "m.sticker", "id": "tg-1157032801921401504", "net.maunium.telegram.sticker": {"pack": {"id": "1157032801921400837", "short_name": "friendsbysmol"}, "id": "1157032801921401504", "emoticons": ["😳"]}}, {"body": "📞", "url": "mxc://matrix.ang-cloud.ru/tcJwZWyfNgHUiHfqkIXEfCYq", "info": {"w": 256, "h": 256, "size": 320439, "mimetype": "image/png", "thumbnail_url": "mxc://matrix.ang-cloud.ru/tcJwZWyfNgHUiHfqkIXEfCYq", "thumbnail_info": {"w": 256, "h": 256, "size": 320439, "mimetype": "image/png"}}, "msgtype": "m.sticker", "id": "tg-1157032801921401506", "net.maunium.telegram.sticker": {"pack": {"id": "1157032801921400837", "short_name": "friendsbysmol"}, "id": "1157032801921401506", "emoticons": ["📞"]}}, {"body": "🍰", "url": "mxc://matrix.ang-cloud.ru/GJpSOtVtOkIdsISXxyNGhNJU", "info": {"w": 256, "h": 256, "size": 297538, "mimetype": "image/png", "thumbnail_url": "mxc://matrix.ang-cloud.ru/GJpSOtVtOkIdsISXxyNGhNJU", "thumbnail_info": {"w": 256, "h": 256, "size": 297538, "mimetype": "image/png"}}, "msgtype": "m.sticker", "id": "tg-1157032801921401508", "net.maunium.telegram.sticker": {"pack": {"id": "1157032801921400837", "short_name": "friendsbysmol"}, "id": "1157032801921401508", "emoticons": ["🍰"]}}, {"body": "😌", "url": "mxc://matrix.ang-cloud.ru/EWNsbprjCOnIyNRMqvNiNAtV", "info": {"w": 256, "h": 256, "size": 444024, "mimetype": "image/png", "thumbnail_url": "mxc://matrix.ang-cloud.ru/EWNsbprjCOnIyNRMqvNiNAtV", "thumbnail_info": {"w": 256, "h": 256, "size": 444024, "mimetype": "image/png"}}, "msgtype": "m.sticker", "id": "tg-1157032801921401510", "net.maunium.telegram.sticker": {"pack": {"id": "1157032801921400837", "short_name": "friendsbysmol"}, "id": "1157032801921401510", "emoticons": ["😌"]}}, {"body": "🍼", "url": "mxc://matrix.ang-cloud.ru/FHqBxxxhZgPNCrOLswFUBVrj", "info": {"w": 256, "h": 256, "size": 446902, "mimetype": "image/png", "thumbnail_url": "mxc://matrix.ang-cloud.ru/FHqBxxxhZgPNCrOLswFUBVrj", "thumbnail_info": {"w": 256, "h": 256, "size": 446902, "mimetype": "image/png"}}, "msgtype": "m.sticker", "id": "tg-1157032801921401512", "net.maunium.telegram.sticker": {"pack": {"id": "1157032801921400837", "short_name": "friendsbysmol"}, "id": "1157032801921401512", "emoticons": ["🍼"]}}, {"body": "😎", "url": "mxc://matrix.ang-cloud.ru/NQjShnqRgkwVQaNaAZPJOcvk", "info": {"w": 256, "h": 256, "size": 347662, "mimetype": "image/png", "thumbnail_url": "mxc://matrix.ang-cloud.ru/NQjShnqRgkwVQaNaAZPJOcvk", "thumbnail_info": {"w": 256, "h": 256, "size": 347662, "mimetype": "image/png"}}, "msgtype": "m.sticker", "id": "tg-1157032801921401514", "net.maunium.telegram.sticker": {"pack": {"id": "1157032801921400837", "short_name": "friendsbysmol"}, "id": "1157032801921401514", "emoticons": ["😎"]}}, {"body": "🤔", "url": "mxc://matrix.ang-cloud.ru/WsaieLYjdZEGCNiWGTkHiIok", "info": {"w": 256, "h": 256, "size": 345663, "mimetype": "image/png", "thumbnail_url": "mxc://matrix.ang-cloud.ru/WsaieLYjdZEGCNiWGTkHiIok", "thumbnail_info": {"w": 256, "h": 256, "size": 345663, "mimetype": "image/png"}}, "msgtype": "m.sticker", "id": "tg-1157032801921401516", "net.maunium.telegram.sticker": {"pack": {"id": "1157032801921400837", "short_name": "friendsbysmol"}, "id": "1157032801921401516", "emoticons": ["🤔"]}}, {"body": "💅", "url": "mxc://matrix.ang-cloud.ru/haJhHkAJRiIIATWaGpnXjxtF", "info": {"w": 256, "h": 256, "size": 468150, "mimetype": "image/png", "thumbnail_url": "mxc://matrix.ang-cloud.ru/haJhHkAJRiIIATWaGpnXjxtF", "thumbnail_info": {"w": 256, "h": 256, "size": 468150, "mimetype": "image/png"}}, "msgtype": "m.sticker", "id": "tg-1157032801921401518", "net.maunium.telegram.sticker": {"pack": {"id": "1157032801921400837", "short_name": "friendsbysmol"}, "id": "1157032801921401518", "emoticons": ["💅"]}}, {"body": "😘", "url": "mxc://matrix.ang-cloud.ru/NLCmhHRIDuMNzZQGHLXTaWxD", "info": {"w": 256, "h": 256, "size": 354086, "mimetype": "image/png", "thumbnail_url": "mxc://matrix.ang-cloud.ru/NLCmhHRIDuMNzZQGHLXTaWxD", "thumbnail_info": {"w": 256, "h": 256, "size": 354086, "mimetype": "image/png"}}, "msgtype": "m.sticker", "id": "tg-1157032801921401520", "net.maunium.telegram.sticker": {"pack": {"id": "1157032801921400837", "short_name": "friendsbysmol"}, "id": "1157032801921401520", "emoticons": ["😘"]}}, {"body": "😍", "url": "mxc://matrix.ang-cloud.ru/XXKCYQUpIzrwyNZWKDlsbgCF", "info": {"w": 256, "h": 256, "size": 310043, "mimetype": "image/png", "thumbnail_url": "mxc://matrix.ang-cloud.ru/XXKCYQUpIzrwyNZWKDlsbgCF", "thumbnail_info": {"w": 256, "h": 256, "size": 310043, "mimetype": "image/png"}}, "msgtype": "m.sticker", "id": "tg-1157032801921401522", "net.maunium.telegram.sticker": {"pack": {"id": "1157032801921400837", "short_name": "friendsbysmol"}, "id": "1157032801921401522", "emoticons": ["😍"]}}, {"body": "👫", "url": "mxc://matrix.ang-cloud.ru/SsKZKyjXycVTqqDuiPYbIIbH", "info": {"w": 256, "h": 256, "size": 441689, "mimetype": "image/png", "thumbnail_url": "mxc://matrix.ang-cloud.ru/SsKZKyjXycVTqqDuiPYbIIbH", "thumbnail_info": {"w": 256, "h": 256, "size": 441689, "mimetype": "image/png"}}, "msgtype": "m.sticker", "id": "tg-1157032801921401524", "net.maunium.telegram.sticker": {"pack": {"id": "1157032801921400837", "short_name": "friendsbysmol"}, "id": "1157032801921401524", "emoticons": ["👫"]}}, {"body": "💃", "url": "mxc://matrix.ang-cloud.ru/gRhWkXMAQnzQriPbKOkdLxXG", "info": {"w": 256, "h": 256, "size": 429413, "mimetype": "image/png", "thumbnail_url": "mxc://matrix.ang-cloud.ru/gRhWkXMAQnzQriPbKOkdLxXG", "thumbnail_info": {"w": 256, "h": 256, "size": 429413, "mimetype": "image/png"}}, "msgtype": "m.sticker", "id": "tg-1157032801921401526", "net.maunium.telegram.sticker": {"pack": {"id": "1157032801921400837", "short_name": "friendsbysmol"}, "id": "1157032801921401526", "emoticons": ["💃"]}}, {"body": "😄", "url": "mxc://matrix.ang-cloud.ru/ZeOoUGjmywiEYkNrzheshnNv", "info": {"w": 256, "h": 256, "size": 371619, "mimetype": "image/png", "thumbnail_url": "mxc://matrix.ang-cloud.ru/ZeOoUGjmywiEYkNrzheshnNv", "thumbnail_info": {"w": 256, "h": 256, "size": 371619, "mimetype": "image/png"}}, "msgtype": "m.sticker", "id": "tg-1157032801921401528", "net.maunium.telegram.sticker": {"pack": {"id": "1157032801921400837", "short_name": "friendsbysmol"}, "id": "1157032801921401528", "emoticons": ["😄"]}}, {"body": "💏", "url": "mxc://matrix.ang-cloud.ru/kkzsNVTtzgGdQGDOkDCotjUY", "info": {"w": 256, "h": 256, "size": 432498, "mimetype": "image/png", "thumbnail_url": "mxc://matrix.ang-cloud.ru/kkzsNVTtzgGdQGDOkDCotjUY", "thumbnail_info": {"w": 256, "h": 256, "size": 432498, "mimetype": "image/png"}}, "msgtype": "m.sticker", "id": "tg-1157032801921401530", "net.maunium.telegram.sticker": {"pack": {"id": "1157032801921400837", "short_name": "friendsbysmol"}, "id": "1157032801921401530", "emoticons": ["💏"]}}, {"body": "🐣", "url": "mxc://matrix.ang-cloud.ru/jSbVfNTZUSRJXmNHzIjoxDEo", "info": {"w": 256, "h": 256, "size": 359434, "mimetype": "image/png", "thumbnail_url": "mxc://matrix.ang-cloud.ru/jSbVfNTZUSRJXmNHzIjoxDEo", "thumbnail_info": {"w": 256, "h": 256, "size": 359434, "mimetype": "image/png"}}, "msgtype": "m.sticker", "id": "tg-1157032801921401532", "net.maunium.telegram.sticker": {"pack": {"id": "1157032801921400837", "short_name": "friendsbysmol"}, "id": "1157032801921401532", "emoticons": ["🐣"]}}, {"body": "😆", "url": "mxc://matrix.ang-cloud.ru/CUJedGXIFLmUnymkrSMIUdNt", "info": {"w": 256, "h": 256, "size": 385361, "mimetype": "image/png", "thumbnail_url": "mxc://matrix.ang-cloud.ru/CUJedGXIFLmUnymkrSMIUdNt", "thumbnail_info": {"w": 256, "h": 256, "size": 385361, "mimetype": "image/png"}}, "msgtype": "m.sticker", "id": "tg-1157032801921401534", "net.maunium.telegram.sticker": {"pack": {"id": "1157032801921400837", "short_name": "friendsbysmol"}, "id": "1157032801921401534", "emoticons": ["😆"]}}, {"body": "😱", "url": "mxc://matrix.ang-cloud.ru/lTbxYTiyekNzZmpTpndKjuRn", "info": {"w": 256, "h": 256, "size": 381238, "mimetype": "image/png", "thumbnail_url": "mxc://matrix.ang-cloud.ru/lTbxYTiyekNzZmpTpndKjuRn", "thumbnail_info": {"w": 256, "h": 256, "size": 381238, "mimetype": "image/png"}}, "msgtype": "m.sticker", "id": "tg-1157032801921401536", "net.maunium.telegram.sticker": {"pack": {"id": "1157032801921400837", "short_name": "friendsbysmol"}, "id": "1157032801921401536", "emoticons": ["😱"]}}, {"body": "🚗", "url": "mxc://matrix.ang-cloud.ru/gGCDHzEgPwctKXtLgMUqjFPC", "info": {"w": 256, "h": 256, "size": 346389, "mimetype": "image/png", "thumbnail_url": "mxc://matrix.ang-cloud.ru/gGCDHzEgPwctKXtLgMUqjFPC", "thumbnail_info": {"w": 256, "h": 256, "size": 346389, "mimetype": "image/png"}}, "msgtype": "m.sticker", "id": "tg-1157032801921401538", "net.maunium.telegram.sticker": {"pack": {"id": "1157032801921400837", "short_name": "friendsbysmol"}, "id": "1157032801921401538", "emoticons": ["🚗"]}}, {"body": "🙌", "url": "mxc://matrix.ang-cloud.ru/HfTkOaypfFVxgPSjkARpilXU", "info": {"w": 256, "h": 256, "size": 348673, "mimetype": "image/png", "thumbnail_url": "mxc://matrix.ang-cloud.ru/HfTkOaypfFVxgPSjkARpilXU", "thumbnail_info": {"w": 256, "h": 256, "size": 348673, "mimetype": "image/png"}}, "msgtype": "m.sticker", "id": "tg-1157032801921401540", "net.maunium.telegram.sticker": {"pack": {"id": "1157032801921400837", "short_name": "friendsbysmol"}, "id": "1157032801921401540", "emoticons": ["🙌"]}}, {"body": "🙉", "url": "mxc://matrix.ang-cloud.ru/bixyiPoTtiBFGLLNVgcnjzNk", "info": {"w": 256, "h": 256, "size": 353506, "mimetype": "image/png", "thumbnail_url": "mxc://matrix.ang-cloud.ru/bixyiPoTtiBFGLLNVgcnjzNk", "thumbnail_info": {"w": 256, "h": 256, "size": 353506, "mimetype": "image/png"}}, "msgtype": "m.sticker", "id": "tg-1157032801921401542", "net.maunium.telegram.sticker": {"pack": {"id": "1157032801921400837", "short_name": "friendsbysmol"}, "id": "1157032801921401542", "emoticons": ["🙉"]}}, {"body": "👀", "url": "mxc://matrix.ang-cloud.ru/KYeeweQrlehOMHeokzOFWuJz", "info": {"w": 256, "h": 256, "size": 331930, "mimetype": "image/png", "thumbnail_url": "mxc://matrix.ang-cloud.ru/KYeeweQrlehOMHeokzOFWuJz", "thumbnail_info": {"w": 256, "h": 256, "size": 331930, "mimetype": "image/png"}}, "msgtype": "m.sticker", "id": "tg-1157032801921401544", "net.maunium.telegram.sticker": {"pack": {"id": "1157032801921400837", "short_name": "friendsbysmol"}, "id": "1157032801921401544", "emoticons": ["👀"]}}, {"body": "😕", "url": "mxc://matrix.ang-cloud.ru/SvUunlQezcssrVzkaJFTmBzC", "info": {"w": 256, "h": 256, "size": 275545, "mimetype": "image/png", "thumbnail_url": "mxc://matrix.ang-cloud.ru/SvUunlQezcssrVzkaJFTmBzC", "thumbnail_info": {"w": 256, "h": 256, "size": 275545, "mimetype": "image/png"}}, "msgtype": "m.sticker", "id": "tg-1157032801921401546", "net.maunium.telegram.sticker": {"pack": {"id": "1157032801921400837", "short_name": "friendsbysmol"}, "id": "1157032801921401546", "emoticons": ["😕"]}}, {"body": "😉", "url": "mxc://matrix.ang-cloud.ru/cNtEPsutgLjPSyCTLBvgOTvS", "info": {"w": 256, "h": 256, "size": 414903, "mimetype": "image/png", "thumbnail_url": "mxc://matrix.ang-cloud.ru/cNtEPsutgLjPSyCTLBvgOTvS", "thumbnail_info": {"w": 256, "h": 256, "size": 414903, "mimetype": "image/png"}}, "msgtype": "m.sticker", "id": "tg-1157032801921401548", "net.maunium.telegram.sticker": {"pack": {"id": "1157032801921400837", "short_name": "friendsbysmol"}, "id": "1157032801921401548", "emoticons": ["😉"]}}, {"body": "🙁", "url": "mxc://matrix.ang-cloud.ru/kfgFZeyRrPQElUUurMbavYcF", "info": {"w": 256, "h": 256, "size": 282636, "mimetype": "image/png", "thumbnail_url": "mxc://matrix.ang-cloud.ru/kfgFZeyRrPQElUUurMbavYcF", "thumbnail_info": {"w": 256, "h": 256, "size": 282636, "mimetype": "image/png"}}, "msgtype": "m.sticker", "id": "tg-1157032801921401550", "net.maunium.telegram.sticker": {"pack": {"id": "1157032801921400837", "short_name": "friendsbysmol"}, "id": "1157032801921401550", "emoticons": ["🙁"]}}, {"body": "😏", "url": "mxc://matrix.ang-cloud.ru/mPWMpUULTwvrjiKPnFtmiFON", "info": {"w": 256, "h": 256, "size": 355262, "mimetype": "image/png", "thumbnail_url": "mxc://matrix.ang-cloud.ru/mPWMpUULTwvrjiKPnFtmiFON", "thumbnail_info": {"w": 256, "h": 256, "size": 355262, "mimetype": "image/png"}}, "msgtype": "m.sticker", "id": "tg-1157032801921401552", "net.maunium.telegram.sticker": {"pack": {"id": "1157032801921400837", "short_name": "friendsbysmol"}, "id": "1157032801921401552", "emoticons": ["😏"]}}, {"body": "📞", "url": "mxc://matrix.ang-cloud.ru/LBKoYWTWBUGLRzUaPDBpLYVx", "info": {"w": 256, "h": 256, "size": 353545, "mimetype": "image/png", "thumbnail_url": "mxc://matrix.ang-cloud.ru/LBKoYWTWBUGLRzUaPDBpLYVx", "thumbnail_info": {"w": 256, "h": 256, "size": 353545, "mimetype": "image/png"}}, "msgtype": "m.sticker", "id": "tg-1157032801921401554", "net.maunium.telegram.sticker": {"pack": {"id": "1157032801921400837", "short_name": "friendsbysmol"}, "id": "1157032801921401554", "emoticons": ["📞"]}}, {"body": "👊", "url": "mxc://matrix.ang-cloud.ru/hXkeWcKOZzYHEEkKgfaNsDAr", "info": {"w": 256, "h": 256, "size": 386850, "mimetype": "image/png", "thumbnail_url": "mxc://matrix.ang-cloud.ru/hXkeWcKOZzYHEEkKgfaNsDAr", "thumbnail_info": {"w": 256, "h": 256, "size": 386850, "mimetype": "image/png"}}, "msgtype": "m.sticker", "id": "tg-1157032801921401556", "net.maunium.telegram.sticker": {"pack": {"id": "1157032801921400837", "short_name": "friendsbysmol"}, "id": "1157032801921401556", "emoticons": ["👊"]}}, {"body": "🍍", "url": "mxc://matrix.ang-cloud.ru/DcViPsieWEaDtOdRXVIHEMWq", "info": {"w": 256, "h": 256, "size": 439243, "mimetype": "image/png", "thumbnail_url": "mxc://matrix.ang-cloud.ru/DcViPsieWEaDtOdRXVIHEMWq", "thumbnail_info": {"w": 256, "h": 256, "size": 439243, "mimetype": "image/png"}}, "msgtype": "m.sticker", "id": "tg-1157032801921401560", "net.maunium.telegram.sticker": {"pack": {"id": "1157032801921400837", "short_name": "friendsbysmol"}, "id": "1157032801921401560", "emoticons": ["🍍"]}}, {"body": "😊", "url": "mxc://matrix.ang-cloud.ru/VdZjTdphZyWcvRwULVUGJDIH", "info": {"w": 256, "h": 256, "size": 349733, "mimetype": "image/png", "thumbnail_url": "mxc://matrix.ang-cloud.ru/VdZjTdphZyWcvRwULVUGJDIH", "thumbnail_info": {"w": 256, "h": 256, "size": 349733, "mimetype": "image/png"}}, "msgtype": "m.sticker", "id": "tg-1157032801921401562", "net.maunium.telegram.sticker": {"pack": {"id": "1157032801921400837", "short_name": "friendsbysmol"}, "id": "1157032801921401562", "emoticons": ["😊"]}}, {"body": "👯", "url": "mxc://matrix.ang-cloud.ru/BvrWYEoXmXuyTsqfGKblQdnk", "info": {"w": 256, "h": 256, "size": 435325, "mimetype": "image/png", "thumbnail_url": "mxc://matrix.ang-cloud.ru/BvrWYEoXmXuyTsqfGKblQdnk", "thumbnail_info": {"w": 256, "h": 256, "size": 435325, "mimetype": "image/png"}}, "msgtype": "m.sticker", "id": "tg-1157032801921401564", "net.maunium.telegram.sticker": {"pack": {"id": "1157032801921400837", "short_name": "friendsbysmol"}, "id": "1157032801921401564", "emoticons": ["👯"]}}, {"body": "🙄", "url": "mxc://matrix.ang-cloud.ru/INbeAmfDxOhOhGBEPlvvdOjc", "info": {"w": 256, "h": 256, "size": 332724, "mimetype": "image/png", "thumbnail_url": "mxc://matrix.ang-cloud.ru/INbeAmfDxOhOhGBEPlvvdOjc", "thumbnail_info": {"w": 256, "h": 256, "size": 332724, "mimetype": "image/png"}}, "msgtype": "m.sticker", "id": "tg-1157032801921401566", "net.maunium.telegram.sticker": {"pack": {"id": "1157032801921400837", "short_name": "friendsbysmol"}, "id": "1157032801921401566", "emoticons": ["🙄"]}}, {"body": "👉", "url": "mxc://matrix.ang-cloud.ru/bfBaoxLakNXfBFKMJaDbFUOO", "info": {"w": 256, "h": 256, "size": 345480, "mimetype": "image/png", "thumbnail_url": "mxc://matrix.ang-cloud.ru/bfBaoxLakNXfBFKMJaDbFUOO", "thumbnail_info": {"w": 256, "h": 256, "size": 345480, "mimetype": "image/png"}}, "msgtype": "m.sticker", "id": "tg-1157032801921401568", "net.maunium.telegram.sticker": {"pack": {"id": "1157032801921400837", "short_name": "friendsbysmol"}, "id": "1157032801921401568", "emoticons": ["👉"]}}, {"body": "😨", "url": "mxc://matrix.ang-cloud.ru/AxJagRIUMcBANGoNejiFbltl", "info": {"w": 256, "h": 256, "size": 382002, "mimetype": "image/png", "thumbnail_url": "mxc://matrix.ang-cloud.ru/AxJagRIUMcBANGoNejiFbltl", "thumbnail_info": {"w": 256, "h": 256, "size": 382002, "mimetype": "image/png"}}, "msgtype": "m.sticker", "id": "tg-1157032801921401570", "net.maunium.telegram.sticker": {"pack": {"id": "1157032801921400837", "short_name": "friendsbysmol"}, "id": "1157032801921401570", "emoticons": ["😨"]}}, {"body": "👱", "url": "mxc://matrix.ang-cloud.ru/DuCNDcgdvafdBWLYTKpyYqyg", "info": {"w": 256, "h": 256, "size": 322569, "mimetype": "image/png", "thumbnail_url": "mxc://matrix.ang-cloud.ru/DuCNDcgdvafdBWLYTKpyYqyg", "thumbnail_info": {"w": 256, "h": 256, "size": 322569, "mimetype": "image/png"}}, "msgtype": "m.sticker", "id": "tg-1157032801921401572", "net.maunium.telegram.sticker": {"pack": {"id": "1157032801921400837", "short_name": "friendsbysmol"}, "id": "1157032801921401572", "emoticons": ["👱"]}}]}