{"title": "stickers2", "id": "stickers2", "stickers": [{"body": "90386", "url": "mxc://matrix.org/mxokeMmCXTQLcWAIWeDYWAUO", "info": {"w": 256, "h": 256, "size": 74912, "mimetype": "image/png", "thumbnail_url": "mxc://matrix.org/mxokeMmCXTQLcWAIWeDYWAUO", "thumbnail_info": {"w": 256, "h": 256, "size": 74912, "mimetype": "image/png"}}, "msgtype": "m.sticker", "id": "sha256:af703998b03e13a305e0d0dae942bce8166c9d2ce72c5d946020bca89158e4c8"}, {"body": "90387", "url": "mxc://matrix.org/YiJPqKNXzHkXjsNJoowQqxPy", "info": {"w": 256, "h": 256, "size": 33003, "mimetype": "image/png", "thumbnail_url": "mxc://matrix.org/YiJPqKNXzHkXjsNJoowQqxPy", "thumbnail_info": {"w": 256, "h": 256, "size": 33003, "mimetype": "image/png"}}, "msgtype": "m.sticker", "id": "sha256:bc4423db2ea9636428dea2274a34ec7ae5f427bb0784fa28d820da5dc2ce2ced"}, {"body": "90388", "url": "mxc://matrix.org/IWjnDlFRcHLNIQWvUXcohmvl", "info": {"w": 256, "h": 256, "size": 50893, "mimetype": "image/png", "thumbnail_url": "mxc://matrix.org/IWjnDlFRcHLNIQWvUXcohmvl", "thumbnail_info": {"w": 256, "h": 256, "size": 50893, "mimetype": "image/png"}}, "msgtype": "m.sticker", "id": "sha256:b5af39e97c14ffad0f6a5c05f348b492eb96655a278f62a705c49310c8c1bcd4"}, {"body": "90389", "url": "mxc://matrix.org/ElbzWypemsiUehfQOHphgHAT", "info": {"w": 256, "h": 256, "size": 43633, "mimetype": "image/png", "thumbnail_url": "mxc://matrix.org/ElbzWypemsiUehfQOHphgHAT", "thumbnail_info": {"w": 256, "h": 256, "size": 43633, "mimetype": "image/png"}}, "msgtype": "m.sticker", "id": "sha256:954dc255937e6ff29fd16421f27a2a41cd49175087cce0ddf38e6dc9abee8870"}, {"body": "90390", "url": "mxc://matrix.org/IClTFLdOjtRfNedfnFUUvcwN", "info": {"w": 256, "h": 256, "size": 42921, "mimetype": "image/png", "thumbnail_url": "mxc://matrix.org/IClTFLdOjtRfNedfnFUUvcwN", "thumbnail_info": {"w": 256, "h": 256, "size": 42921, "mimetype": "image/png"}}, "msgtype": "m.sticker", "id": "sha256:450061efb64e879f02bd674a2bb4a3df68d36b187f19d3ed487cd8857793c79d"}, {"body": "90391", "url": "mxc://matrix.org/ONOXTfnCFzYEAmGtdvIscLKl", "info": {"w": 256, "h": 256, "size": 52117, "mimetype": "image/png", "thumbnail_url": "mxc://matrix.org/ONOXTfnCFzYEAmGtdvIscLKl", "thumbnail_info": {"w": 256, "h": 256, "size": 52117, "mimetype": "image/png"}}, "msgtype": "m.sticker", "id": "sha256:7bb363e8d878b7fa3b311a3ba64dc1299e342428aecda6dddbe87c02e055bc1e"}, {"body": "90392", "url": "mxc://matrix.org/urQIfcazOfjRGWIWkZMmjKHG", "info": {"w": 256, "h": 256, "size": 56856, "mimetype": "image/png", "thumbnail_url": "mxc://matrix.org/urQIfcazOfjRGWIWkZMmjKHG", "thumbnail_info": {"w": 256, "h": 256, "size": 56856, "mimetype": "image/png"}}, "msgtype": "m.sticker", "id": "sha256:6ce420e32c599840bb988d7842625baa40631ead7b87faa02351023b9f3e52cf"}, {"body": "90393", "url": "mxc://matrix.org/XcnlYErBBcQFgcCZYIzLDCsj", "info": {"w": 256, "h": 256, "size": 47690, "mimetype": "image/png", "thumbnail_url": "mxc://matrix.org/XcnlYErBBcQFgcCZYIzLDCsj", "thumbnail_info": {"w": 256, "h": 256, "size": 47690, "mimetype": "image/png"}}, "msgtype": "m.sticker", "id": "sha256:dc0d8e9175fa39f6ef849b524f073125e5f350467accbbd60128b3cb01757269"}, {"body": "90394", "url": "mxc://matrix.org/cskNLYLJDcDiZhLumkGqiKDL", "info": {"w": 256, "h": 256, "size": 31199, "mimetype": "image/png", "thumbnail_url": "mxc://matrix.org/cskNLYLJDcDiZhLumkGqiKDL", "thumbnail_info": {"w": 256, "h": 256, "size": 31199, "mimetype": "image/png"}}, "msgtype": "m.sticker", "id": "sha256:607bb4d077dd1c9dabe9a0f3b3d6cf23bf4c2bd4dadace5a5aff46852612eaab"}, {"body": "90395", "url": "mxc://matrix.org/uJwkuYQFOWROEEavnQDjoUuj", "info": {"w": 256, "h": 256, "size": 55206, "mimetype": "image/png", "thumbnail_url": "mxc://matrix.org/uJwkuYQFOWROEEavnQDjoUuj", "thumbnail_info": {"w": 256, "h": 256, "size": 55206, "mimetype": "image/png"}}, "msgtype": "m.sticker", "id": "sha256:62184774a046ed2a9ee0a82204384696808169158a9659d2c5833bd6788c12fc"}, {"body": "90396", "url": "mxc://matrix.org/lRFfpswtzFgcGHTXUqUqkPcQ", "info": {"w": 256, "h": 256, "size": 44112, "mimetype": "image/png", "thumbnail_url": "mxc://matrix.org/lRFfpswtzFgcGHTXUqUqkPcQ", "thumbnail_info": {"w": 256, "h": 256, "size": 44112, "mimetype": "image/png"}}, "msgtype": "m.sticker", "id": "sha256:552f17bf884040906ada7909c4f80d50ae729564cc7965597867eff93a000f75"}, {"body": "90397", "url": "mxc://matrix.org/FnkkNLEOPmgYcXbNQAjccbOM", "info": {"w": 256, "h": 256, "size": 55418, "mimetype": "image/png", "thumbnail_url": "mxc://matrix.org/FnkkNLEOPmgYcXbNQAjccbOM", "thumbnail_info": {"w": 256, "h": 256, "size": 55418, "mimetype": "image/png"}}, "msgtype": "m.sticker", "id": "sha256:de4d48c265a95d7585037e9726a9af85f7914d5167d556ff289fcb0d2c5e7f0e"}, {"body": "90398", "url": "mxc://matrix.org/UUOsXZdXcSonnRGVnodhNwCQ", "info": {"w": 256, "h": 256, "size": 47628, "mimetype": "image/png", "thumbnail_url": "mxc://matrix.org/UUOsXZdXcSonnRGVnodhNwCQ", "thumbnail_info": {"w": 256, "h": 256, "size": 47628, "mimetype": "image/png"}}, "msgtype": "m.sticker", "id": "sha256:ecea24d2320497e341f31ceb119c6b8018cf1be0d2f499860188ec9dffb3a476"}, {"body": "90399", "url": "mxc://matrix.org/fbKzhBqLHaCIWbfhlWzKZTut", "info": {"w": 256, "h": 256, "size": 54584, "mimetype": "image/png", "thumbnail_url": "mxc://matrix.org/fbKzhBqLHaCIWbfhlWzKZTut", "thumbnail_info": {"w": 256, "h": 256, "size": 54584, "mimetype": "image/png"}}, "msgtype": "m.sticker", "id": "sha256:aa4ceb2be47e92d8260c66c4e7b2b248e3e49810faf6e43cf0d4c0f98d202a05"}, {"body": "90400", "url": "mxc://matrix.org/sSPJwZIZPfSVhUKyVyAcZQee", "info": {"w": 256, "h": 256, "size": 44930, "mimetype": "image/png", "thumbnail_url": "mxc://matrix.org/sSPJwZIZPfSVhUKyVyAcZQee", "thumbnail_info": {"w": 256, "h": 256, "size": 44930, "mimetype": "image/png"}}, "msgtype": "m.sticker", "id": "sha256:5dc4e733b5cd2ced8bc7005efe8a486c2a91358d74344bb79a1223ecd9ce6a74"}, {"body": "90401", "url": "mxc://matrix.org/tUMduclhUgenEKOmactmEniA", "info": {"w": 256, "h": 256, "size": 71308, "mimetype": "image/png", "thumbnail_url": "mxc://matrix.org/tUMduclhUgenEKOmactmEniA", "thumbnail_info": {"w": 256, "h": 256, "size": 71308, "mimetype": "image/png"}}, "msgtype": "m.sticker", "id": "sha256:0224672dd9cd0c9ee2a61538faafa7a1c1ba0a0a2518ca71f52c21fb16947d82"}, {"body": "90402", "url": "mxc://matrix.org/cEguNVnSnyXWTmfTVDGXlMxX", "info": {"w": 256, "h": 256, "size": 46242, "mimetype": "image/png", "thumbnail_url": "mxc://matrix.org/cEguNVnSnyXWTmfTVDGXlMxX", "thumbnail_info": {"w": 256, "h": 256, "size": 46242, "mimetype": "image/png"}}, "msgtype": "m.sticker", "id": "sha256:370caf813e10993ec1069202b1a436fb64d895f880a035088058b54a982b30f1"}, {"body": "90403", "url": "mxc://matrix.org/jsbDpUXxKvgZZokqakbihBaI", "info": {"w": 256, "h": 256, "size": 58802, "mimetype": "image/png", "thumbnail_url": "mxc://matrix.org/jsbDpUXxKvgZZokqakbihBaI", "thumbnail_info": {"w": 256, "h": 256, "size": 58802, "mimetype": "image/png"}}, "msgtype": "m.sticker", "id": "sha256:17510dba549021d3a87d38fb4ff193a0c78618540b662b09d322fd28065b87f3"}, {"body": "90404", "url": "mxc://matrix.org/psMwfJJsGNcccrjAivQHYQFQ", "info": {"w": 256, "h": 256, "size": 31315, "mimetype": "image/png", "thumbnail_url": "mxc://matrix.org/psMwfJJsGNcccrjAivQHYQFQ", "thumbnail_info": {"w": 256, "h": 256, "size": 31315, "mimetype": "image/png"}}, "msgtype": "m.sticker", "id": "sha256:b101da5aec4315c54da9820ea4fc429555b01c1037618ee9c5949befe9baa8e3"}, {"body": "90405", "url": "mxc://matrix.org/rbYgBlVVzrEabCestAOkkchQ", "info": {"w": 256, "h": 256, "size": 30083, "mimetype": "image/png", "thumbnail_url": "mxc://matrix.org/rbYgBlVVzrEabCestAOkkchQ", "thumbnail_info": {"w": 256, "h": 256, "size": 30083, "mimetype": "image/png"}}, "msgtype": "m.sticker", "id": "sha256:91e6cfa27bd1b2141899ae80d57c95cb99cd7d76dbaed761cf17024de3e86008"}, {"body": "90406", "url": "mxc://matrix.org/NnIZNnNpekZZBzKpOvqXqOlf", "info": {"w": 256, "h": 256, "size": 48955, "mimetype": "image/png", "thumbnail_url": "mxc://matrix.org/NnIZNnNpekZZBzKpOvqXqOlf", "thumbnail_info": {"w": 256, "h": 256, "size": 48955, "mimetype": "image/png"}}, "msgtype": "m.sticker", "id": "sha256:1417baa5c3c9d9075d33fac5b0bc1015d874cfc7e98fba90a0d49fc74458e8ef"}, {"body": "90407", "url": "mxc://matrix.org/ItYeBWjjCLoioAxfPHpzEkCO", "info": {"w": 256, "h": 256, "size": 48689, "mimetype": "image/png", "thumbnail_url": "mxc://matrix.org/ItYeBWjjCLoioAxfPHpzEkCO", "thumbnail_info": {"w": 256, "h": 256, "size": 48689, "mimetype": "image/png"}}, "msgtype": "m.sticker", "id": "sha256:23f8a1b16aa76d5fffc9972c14c07da9fc13153bf5524550708155f245e7951e"}, {"body": "90408", "url": "mxc://matrix.org/wrwmlQMLpDSrfPARnJjHoddK", "info": {"w": 256, "h": 256, "size": 27727, "mimetype": "image/png", "thumbnail_url": "mxc://matrix.org/wrwmlQMLpDSrfPARnJjHoddK", "thumbnail_info": {"w": 256, "h": 256, "size": 27727, "mimetype": "image/png"}}, "msgtype": "m.sticker", "id": "sha256:fbd59904ee0815eb8489d72916379ae2b7e728dafea2a2015b5e3a8293384ea4"}, {"body": "90409", "url": "mxc://matrix.org/hiZIepAAYAkzCSgEknDhKgds", "info": {"w": 256, "h": 256, "size": 33730, "mimetype": "image/png", "thumbnail_url": "mxc://matrix.org/hiZIepAAYAkzCSgEknDhKgds", "thumbnail_info": {"w": 256, "h": 256, "size": 33730, "mimetype": "image/png"}}, "msgtype": "m.sticker", "id": "sha256:f91a5bb3ee42960f84370cab648b60a689055f709fe9bd73fd1286017fc98fe0"}, {"body": "90410", "url": "mxc://matrix.org/NfCtffkRLErEFmeXwaGLVxfs", "info": {"w": 256, "h": 256, "size": 36071, "mimetype": "image/png", "thumbnail_url": "mxc://matrix.org/NfCtffkRLErEFmeXwaGLVxfs", "thumbnail_info": {"w": 256, "h": 256, "size": 36071, "mimetype": "image/png"}}, "msgtype": "m.sticker", "id": "sha256:ac704f5ef14c6c99fcf70d3bc8cf3a2176c6ca87df5568c21fa4e5d4bcc4e986"}, {"body": "90411", "url": "mxc://matrix.org/vEbpLnKUfrhRkzHOtqAyjXbM", "info": {"w": 256, "h": 256, "size": 37823, "mimetype": "image/png", "thumbnail_url": "mxc://matrix.org/vEbpLnKUfrhRkzHOtqAyjXbM", "thumbnail_info": {"w": 256, "h": 256, "size": 37823, "mimetype": "image/png"}}, "msgtype": "m.sticker", "id": "sha256:ec1b8a7f9d428597357882e344200c6d4065461c99139e639d62d804e620345f"}, {"body": "90412", "url": "mxc://matrix.org/FmUbrSQnKArFoGsuFfDEDFTG", "info": {"w": 256, "h": 256, "size": 47373, "mimetype": "image/png", "thumbnail_url": "mxc://matrix.org/FmUbrSQnKArFoGsuFfDEDFTG", "thumbnail_info": {"w": 256, "h": 256, "size": 47373, "mimetype": "image/png"}}, "msgtype": "m.sticker", "id": "sha256:d1d404d3f38311b3491701a352b7c6a8d7912a286d63a5343427b0c64506288f"}, {"body": "90413", "url": "mxc://matrix.org/XVwwoPIsaPIfWNtqyQkUjXnZ", "info": {"w": 256, "h": 256, "size": 39306, "mimetype": "image/png", "thumbnail_url": "mxc://matrix.org/XVwwoPIsaPIfWNtqyQkUjXnZ", "thumbnail_info": {"w": 256, "h": 256, "size": 39306, "mimetype": "image/png"}}, "msgtype": "m.sticker", "id": "sha256:7f3a5b3ac29f1dcf76b126c9d2ce0ee24349a0cfee33180caf959e3b734d7eee"}, {"body": "90414", "url": "mxc://matrix.org/JfDkbXgMrJXOLKvJqYhIHWHG", "info": {"w": 256, "h": 256, "size": 40381, "mimetype": "image/png", "thumbnail_url": "mxc://matrix.org/JfDkbXgMrJXOLKvJqYhIHWHG", "thumbnail_info": {"w": 256, "h": 256, "size": 40381, "mimetype": "image/png"}}, "msgtype": "m.sticker", "id": "sha256:489507ff952c1b79bc312e465d57036ceb609e63231d194edab2955739ebed8a"}, {"body": "90415", "url": "mxc://matrix.org/bUVHtcihwkvcCpKbbgojzKLi", "info": {"w": 256, "h": 256, "size": 59591, "mimetype": "image/png", "thumbnail_url": "mxc://matrix.org/bUVHtcihwkvcCpKbbgojzKLi", "thumbnail_info": {"w": 256, "h": 256, "size": 59591, "mimetype": "image/png"}}, "msgtype": "m.sticker", "id": "sha256:17a4a994d7bc292837ac48524a3f4ca97100c348d2c7be85a546a9de313ce738"}, {"body": "90416", "url": "mxc://matrix.org/lTlsnGooMvQDJNXLwPVEEBWv", "info": {"w": 256, "h": 256, "size": 31548, "mimetype": "image/png", "thumbnail_url": "mxc://matrix.org/lTlsnGooMvQDJNXLwPVEEBWv", "thumbnail_info": {"w": 256, "h": 256, "size": 31548, "mimetype": "image/png"}}, "msgtype": "m.sticker", "id": "sha256:0ab1f91ce72ad6639388f03f9639f9a638808e59766afd5aaa4e97a6898bf111"}, {"body": "90417", "url": "mxc://matrix.org/yjQEIjyHlDxUgwOXIrIryspv", "info": {"w": 256, "h": 256, "size": 41460, "mimetype": "image/png", "thumbnail_url": "mxc://matrix.org/yjQEIjyHlDxUgwOXIrIryspv", "thumbnail_info": {"w": 256, "h": 256, "size": 41460, "mimetype": "image/png"}}, "msgtype": "m.sticker", "id": "sha256:b761bcb2b32ab276247895e134bcf78578530d6d6b1c9186e717743d2ea9fca3"}, {"body": "90418", "url": "mxc://matrix.org/urzVqufrMlUBLsUamAdPlxRM", "info": {"w": 256, "h": 256, "size": 61197, "mimetype": "image/png", "thumbnail_url": "mxc://matrix.org/urzVqufrMlUBLsUamAdPlxRM", "thumbnail_info": {"w": 256, "h": 256, "size": 61197, "mimetype": "image/png"}}, "msgtype": "m.sticker", "id": "sha256:0b3982429072f2fff73361a6a315aecf6550e6e93e313600f7a7481377a7af08"}, {"body": "90419", "url": "mxc://matrix.org/MKlftrdqHFXRHsPRbUtiKFcD", "info": {"w": 256, "h": 256, "size": 38655, "mimetype": "image/png", "thumbnail_url": "mxc://matrix.org/MKlftrdqHFXRHsPRbUtiKFcD", "thumbnail_info": {"w": 256, "h": 256, "size": 38655, "mimetype": "image/png"}}, "msgtype": "m.sticker", "id": "sha256:007118309e1990b867f35efbb621f41a2286609f17964c5f9e5e5d861cbe7590"}, {"body": "90420", "url": "mxc://matrix.org/ErBdFCTszpGEamuZHTusKRql", "info": {"w": 256, "h": 256, "size": 47012, "mimetype": "image/png", "thumbnail_url": "mxc://matrix.org/ErBdFCTszpGEamuZHTusKRql", "thumbnail_info": {"w": 256, "h": 256, "size": 47012, "mimetype": "image/png"}}, "msgtype": "m.sticker", "id": "sha256:a0fb688e6f05386638c87c6fb423aaa85bc3f0084024569b1e7f9e8ee32b9949"}, {"body": "90421", "url": "mxc://matrix.org/FvgfVfIucSXZazhWEcZWArso", "info": {"w": 256, "h": 256, "size": 49642, "mimetype": "image/png", "thumbnail_url": "mxc://matrix.org/FvgfVfIucSXZazhWEcZWArso", "thumbnail_info": {"w": 256, "h": 256, "size": 49642, "mimetype": "image/png"}}, "msgtype": "m.sticker", "id": "sha256:abc749c0c03591947754d9921468f3d05efb64f7c33cdfc46d5a48e7aeee3751"}, {"body": "90422", "url": "mxc://matrix.org/qDyDPcEqBPrGhlVLVuWHViNw", "info": {"w": 256, "h": 256, "size": 48765, "mimetype": "image/png", "thumbnail_url": "mxc://matrix.org/qDyDPcEqBPrGhlVLVuWHViNw", "thumbnail_info": {"w": 256, "h": 256, "size": 48765, "mimetype": "image/png"}}, "msgtype": "m.sticker", "id": "sha256:1a09637df01686b282c68f9b2fa43ad6a4e16fff26d74514a256439420c29393"}, {"body": "90423", "url": "mxc://matrix.org/zcFaosXJsVauPoIZlACIZSwj", "info": {"w": 256, "h": 256, "size": 37190, "mimetype": "image/png", "thumbnail_url": "mxc://matrix.org/zcFaosXJsVauPoIZlACIZSwj", "thumbnail_info": {"w": 256, "h": 256, "size": 37190, "mimetype": "image/png"}}, "msgtype": "m.sticker", "id": "sha256:42a96b9a40251fd977ff60f9d1e6780409c8e20968cbe8967bfa5e117a0a7a2b"}, {"body": "90424", "url": "mxc://matrix.org/CPGPFDZlYOTeYOggxfYSARar", "info": {"w": 256, "h": 256, "size": 41941, "mimetype": "image/png", "thumbnail_url": "mxc://matrix.org/CPGPFDZlYOTeYOggxfYSARar", "thumbnail_info": {"w": 256, "h": 256, "size": 41941, "mimetype": "image/png"}}, "msgtype": "m.sticker", "id": "sha256:684223d17f8d8bf21d05d335f361d0dbe87b3a90aa28a6beb5e72bc0b8525f5c"}, {"body": "90425", "url": "mxc://matrix.org/FpqvaLdiRyifTITndxqiLQGD", "info": {"w": 256, "h": 256, "size": 45398, "mimetype": "image/png", "thumbnail_url": "mxc://matrix.org/FpqvaLdiRyifTITndxqiLQGD", "thumbnail_info": {"w": 256, "h": 256, "size": 45398, "mimetype": "image/png"}}, "msgtype": "m.sticker", "id": "sha256:b52454412839128231adde94d3b6d589452f9dbabc8a4c28ca23694a3a260b17"}, {"body": "90426", "url": "mxc://matrix.org/GydpecIrTdVXbNzVmoYAEHmE", "info": {"w": 256, "h": 256, "size": 64598, "mimetype": "image/png", "thumbnail_url": "mxc://matrix.org/GydpecIrTdVXbNzVmoYAEHmE", "thumbnail_info": {"w": 256, "h": 256, "size": 64598, "mimetype": "image/png"}}, "msgtype": "m.sticker", "id": "sha256:4999e5453b282d1c417dba53fe34d3654e9abc88cf737d99668d6c1935ac4225"}, {"body": "90427", "url": "mxc://matrix.org/lMLPPOkXICWUVpkGwdOdnTjP", "info": {"w": 256, "h": 256, "size": 64840, "mimetype": "image/png", "thumbnail_url": "mxc://matrix.org/lMLPPOkXICWUVpkGwdOdnTjP", "thumbnail_info": {"w": 256, "h": 256, "size": 64840, "mimetype": "image/png"}}, "msgtype": "m.sticker", "id": "sha256:ea960c4fbdd4f0e10378e4e94461061ff606a6106afb8f76bf79fac6e1f0212c"}, {"body": "90428", "url": "mxc://matrix.org/KMBBYZmpWupETyyZXNXvvtiV", "info": {"w": 256, "h": 256, "size": 29686, "mimetype": "image/png", "thumbnail_url": "mxc://matrix.org/KMBBYZmpWupETyyZXNXvvtiV", "thumbnail_info": {"w": 256, "h": 256, "size": 29686, "mimetype": "image/png"}}, "msgtype": "m.sticker", "id": "sha256:c18b2e1fbbab15e7db1a9c45246601412bf02a9820fdf29375a575625f63bac0"}, {"body": "90429", "url": "mxc://matrix.org/yKPjVYdNPNPksashEDuGBqSO", "info": {"w": 256, "h": 256, "size": 63502, "mimetype": "image/png", "thumbnail_url": "mxc://matrix.org/yKPjVYdNPNPksashEDuGBqSO", "thumbnail_info": {"w": 256, "h": 256, "size": 63502, "mimetype": "image/png"}}, "msgtype": "m.sticker", "id": "sha256:45d1c8a2b84fdbf19c6f1a069c7f64bc26acc4cab9e4c6dd7e54fbf7edfdf49a"}, {"body": "90430", "url": "mxc://matrix.org/YTyDVCwUrnpLUvKEWNXqDmNZ", "info": {"w": 256, "h": 256, "size": 45373, "mimetype": "image/png", "thumbnail_url": "mxc://matrix.org/YTyDVCwUrnpLUvKEWNXqDmNZ", "thumbnail_info": {"w": 256, "h": 256, "size": 45373, "mimetype": "image/png"}}, "msgtype": "m.sticker", "id": "sha256:bbafe38ed887f5669e9069d41203b9a03005dc9ea02505f37c7f33e2694d3502"}, {"body": "90431", "url": "mxc://matrix.org/SucvynMBeSeathLngJkLWogM", "info": {"w": 256, "h": 256, "size": 48195, "mimetype": "image/png", "thumbnail_url": "mxc://matrix.org/SucvynMBeSeathLngJkLWogM", "thumbnail_info": {"w": 256, "h": 256, "size": 48195, "mimetype": "image/png"}}, "msgtype": "m.sticker", "id": "sha256:af186b1c6deac3840388a90c2e18dee74a23b8d1ad2b9ce8ee91bbc62be0f27e"}, {"body": "90432", "url": "mxc://matrix.org/wWeYfoLRCzoTxkNixmjnDDAN", "info": {"w": 256, "h": 256, "size": 51356, "mimetype": "image/png", "thumbnail_url": "mxc://matrix.org/wWeYfoLRCzoTxkNixmjnDDAN", "thumbnail_info": {"w": 256, "h": 256, "size": 51356, "mimetype": "image/png"}}, "msgtype": "m.sticker", "id": "sha256:4fe38a1aa9e3302b1952160f80db1675c52385ec405aa87175d9be97330d9ab2"}, {"body": "90433", "url": "mxc://matrix.org/pEJPVKMxBxnZeVqlpQllCbJH", "info": {"w": 256, "h": 256, "size": 38129, "mimetype": "image/png", "thumbnail_url": "mxc://matrix.org/pEJPVKMxBxnZeVqlpQllCbJH", "thumbnail_info": {"w": 256, "h": 256, "size": 38129, "mimetype": "image/png"}}, "msgtype": "m.sticker", "id": "sha256:27a15b978ddb526263f2fd86b2736a25c040a1e7e7119d117b6c72360c1ee50f"}]}